Workbook
Name cid: customersdata[Cust_ID]
Name Cust_ID: [1]!customersdata[Cust_ID]
Name HSNCode: [1]!Table4[HSN Code]

Sheet Dashboard
N15: Notifications !
N18: {=_xlfn._xlws.FILTER(Inventory!K11:K12,8,0)} -> 📞 Smart Watch Needs to re-order ! PH 9812xxxxxx
N19: 📞 Laptop HP xyz i5 Needs to re-order ! PH 9813xxxxxx
N20: {=_xlfn._xlws.FILTER(Inventory!K14,8,0)} -> 📞 Desktop Needs to re-order ! PH 9813xxxxxx
N21: {=_xlfn._xlws.FILTER(Inventory!K16,8,0)} -> 📞 Rgb Keyboard Needs to re-order ! PH 9814xxxxxx

Sheet Customers
D8: Cust_ID | E8: Name | F8: Email | G8: Address
D9: 100 | E9: Ram sales | F9: Ram@gmail.com | G9: Delhi, India
D10: 101 | E10: Atul Ltd. | F10: Atu@gmail.com | G10: 121102, Palwal, HR
D11: 102 | E11: MK Tech. | F11: MK @gmail.com | G11: Faridabad, 121101
D12: 103 | E12: 99store | F12: 99s@gmail.com | G12: Agra, UP
D13: 104 | E13: Rajesh Kumar | F13: Raj@gmail.com | G13: New Delhi, 110011
D14: 105 | E14: Amit | F14: Ami@gmail.com | G14: Gurgaon, Sec-15
D15: 106 | E15: Jain Tel. | F15: Jai@gmail.com | G15: Janpath, New Delhi

Sheet Products
D8: HSN Code | E8: Product Name | F8: Cost | G8: Selling Price
D9: N1001 | E9: Smart Watch | F9: 980 | G9: 1176
D10: N1002 | E10: Laptop HP xyz i5 | F10: 34500 | G10: 41400
D11: N1003 | E11: Wireless Printer | F11: 4600 | G11: 5520
D12: N1004 | E12: Desktop | F12: 21000 | G12: 25200
D13: N1005 | E13: Mouse | F13: 200 | G13: 240
D14: N1006 | E14: Rgb Keyboard | F14: 340 | G14: 408
D15: N1007 | E15: Camera | F15: 52000 | G15: 62400
D16: N1008 | E16: Headphones | F16: 799 | G16: 958.8
D17: N1009 | E17: Speakers | F17: 670 | G17: 804
D18: N1010 | E18: Tablets | F18: 23500 | G18: 28200

Sheet Vendors
D8: HSN Code | E8: Product Name | F8: Vendor Name | G8: Phone | H8: Address
D9: N1001 | E9: Smart Watch | F9: Tech99 | G9: 9812xxxxxx | H9: Faridabad, 121101
D10: N1002 | E10: Laptop HP xyz i5 | F10: Tech99 | G10: 9812xxxxxx | H10: Faridabad, 121102
D11: N1003 | E11: Wireless Printer | F11: Tech99 | G11: 9812xxxxxx | H11: Faridabad, 121103
D12: N1004 | E12: Desktop | F12: GG Traders | G12: 9813xxxxxx | H12: Gurgaon, Sec-15
D13: N1005 | E13: Mouse | F13: GG Traders | G13: 9813xxxxxx | H13: Gurgaon, Sec-16
D14: N1006 | E14: Rgb Keyboard | F14: GG Traders | G14: 9813xxxxxx | H14: Gurgaon, Sec-17
D15: N1007 | E15: Camera | F15: GG Traders | G15: 9813xxxxxx | H15: Gurgaon, Sec-18
D16: N1008 | E16: Headphones | F16: Compac | G16: 9814xxxxxx | H16: New Delhi, 110012
D17: N1009 | E17: Speakers | F17: Compac | G17: 9814xxxxxx | H17: New Delhi, 110013
D18: N1010 | E18: Tablets | F18: Compac | G18: 9814xxxxxx | H18: New Delhi, 110014

Sheet New Entry Purchase
F11: Purchase Entry
F14: Sales Entry

Sheet Purchase
D9: HSN Code | E9: Product Name | F9: Vendor | G9: Date | H9: Unit | I9: Cost | J9: Amount
D10: N1001 | E10: =VLOOKUP(purchasedata[[#This Row],[HSN Code]],Table4[#All],2,0) -> Smart Watch | F10: =VLOOKUP(purchasedata[[#This Row],[HSN Code]],vendorsdata[#All],3,0) -> Tech99 | H10: 40 | I10: =VLOOKUP(purchasedata[[#This Row],[HSN Code]],Table4[#All],3,0) -> 980 | J10: =purchasedata[[#This Row],[Unit]]*purchasedata[[#This Row],[Cost]] -> 39200
D11: N1001 | E11: =VLOOKUP(purchasedata[[#This Row],[HSN Code]],Table4[#All],2,0) -> Smart Watch | F11: =VLOOKUP(purchasedata[[#This Row],[HSN Code]],vendorsdata[#All],3,0) -> Tech99 | G11: 45292 | H11: 40 | I11: =VLOOKUP(purchasedata[[#This Row],[HSN Code]],Table4[#All],3,0) -> 980 | J11: =purchasedata[[#This Row],[Unit]]*purchasedata[[#This Row],[Cost]] -> 39200
D12: N1002 | E12: =VLOOKUP(purchasedata[[#This Row],[HSN Code]],Table4[#All],2,0) -> Laptop HP xyz i5 | F12: =VLOOKUP(purchasedata[[#This Row],[HSN Code]],vendorsdata[#All],3,0) -> Tech99 | G12: 45293 | H12: 30 | I12: =VLOOKUP(purchasedata[[#This Row],[HSN Code]],Table4[#All],3,0) -> 34500 | J12: =purchasedata[[#This Row],[Unit]]*purchasedata[[#This Row],[Cost]] -> 1035000
D13: N1003 | E13: =VLOOKUP(purchasedata[[#This Row],[HSN Code]],Table4[#All],2,0) -> Wireless Printer | F13: =VLOOKUP(purchasedata[[#This Row],[HSN Code]],vendorsdata[#All],3,0) -> Tech99 | G13: 45294 | H13: 40 | I13: =VLOOKUP(purchasedata[[#This Row],[HSN Code]],Table4[#All],3,0) -> 4600 | J13: =purchasedata[[#This Row],[Unit]]*purchasedata[[#This Row],[Cost]] -> 184000
D14: N1004 | E14: =VLOOKUP(purchasedata[[#This Row],[HSN Code]],Table4[#All],2,0) -> Desktop | F14: =VLOOKUP(purchasedata[[#This Row],[HSN Code]],vendorsdata[#All],3,0) -> GG Traders | G14: 45295 | H14: 100 | I14: =VLOOKUP(purchasedata[[#This Row],[HSN Code]],Table4[#All],3,0) -> 21000 | J14: =purchasedata[[#This Row],[Unit]]*purchasedata[[#This Row],[Cost]] -> 2100000
D15: N1005 | E15: =VLOOKUP(purchasedata[[#This Row],[HSN Code]],Table4[#All],2,0) -> Mouse | F15: =VLOOKUP(purchasedata[[#This Row],[HSN Code]],vendorsdata[#All],3,0) -> GG Traders | G15: 45296 | H15: 20 | I15: =VLOOKUP(purchasedata[[#This Row],[HSN Code]],Table4[#All],3,0) -> 200 | J15: =purchasedata[[#This Row],[Unit]]*purchasedata[[#This Row],[Cost]] -> 4000
D16: N1006 | E16: =VLOOKUP(purchasedata[[#This Row],[HSN Code]],Table4[#All],2,0) -> Rgb Keyboard | F16: =VLOOKUP(purchasedata[[#This Row],[HSN Code]],vendorsdata[#All],3,0) -> GG Traders | G16: 45297 | H16: 50 | I16: =VLOOKUP(purchasedata[[#This Row],[HSN Code]],Table4[#All],3,0) -> 340 | J16: =purchasedata[[#This Row],[Unit]]*purchasedata[[#This Row],[Cost]] -> 17000
D17: N1007 | E17: =VLOOKUP(purchasedata[[#This Row],[HSN Code]],Table4[#All],2,0) -> Camera | F17: =VLOOKUP(purchasedata[[#This Row],[HSN Code]],vendorsdata[#All],3,0) -> GG Traders | G17: 45298 | H17: 20 | I17: =VLOOKUP(purchasedata[[#This Row],[HSN Code]],Table4[#All],3,0) -> 52000 | J17: =purchasedata[[#This Row],[Unit]]*purchasedata[[#This Row],[Cost]] -> 1040000
D18: N1008 | E18: =VLOOKUP(purchasedata[[#This Row],[HSN Code]],Table4[#All],2,0) -> Headphones | F18: =VLOOKUP(purchasedata[[#This Row],[HSN Code]],vendorsdata[#All],3,0) -> Compac | G18: 45299 | H18: 35 | I18: =VLOOKUP(purchasedata[[#This Row],[HSN Code]],Table4[#All],3,0) -> 799 | J18: =purchasedata[[#This Row],[Unit]]*purchasedata[[#This Row],[Cost]] -> 27965
D19: N1009 | E19: =VLOOKUP(purchasedata[[#This Row],[HSN Code]],Table4[#All],2,0) -> Speakers | F19: =VLOOKUP(purchasedata[[#This Row],[HSN Code]],vendorsdata[#All],3,0) -> Compac | G19: 45300 | H19: 55 | I19: =VLOOKUP(purchasedata[[#This Row],[HSN Code]],Table4[#All],3,0) -> 670 | J19: =purchasedata[[#This Row],[Unit]]*purchasedata[[#This Row],[Cost]] -> 36850
D20: N1010 | E20: =VLOOKUP(purchasedata[[#This Row],[HSN Code]],Table4[#All],2,0) -> Tablets | F20: =VLOOKUP(purchasedata[[#This Row],[HSN Code]],vendorsdata[#All],3,0) -> Compac | G20: 45301 | H20: 40 | I20: =VLOOKUP(purchasedata[[#This Row],[HSN Code]],Table4[#All],3,0) -> 23500 | J20: =purchasedata[[#This Row],[Unit]]*purchasedata[[#This Row],[Cost]] -> 940000

Sheet Sales
D8: Cust_ID | E8: Cust_Name | F8: HSN Code | G8: Product Name | H8: Date | I8: Stock(Units) | J8: Units | K8: Price | L8: Amount
D9: 100 | E9: =VLOOKUP(salesdata[[#This Row],[Cust_ID]],customersdata[#All],2,0) -> Ram sales | F9: N1001 | G9: =VLOOKUP(salesdata[[#This Row],[HSN Code]],Table4[#All],2,0) -> Smart Watch | I9: =VLOOKUP(salesdata[[#This Row],[HSN Code]],Table3[#All],6,0) -> 13 | J9: 27 | K9: =VLOOKUP(salesdata[[#This Row],[HSN Code]],Table4[#All],4,0) -> 1176 | L9: =salesdata[[#This Row],[Price]]*salesdata[[#This Row],[Units]] -> 31752
D10: 101 | E10: =VLOOKUP(salesdata[[#This Row],[Cust_ID]],customersdata[#All],2,0) -> Atul Ltd. | F10: N1002 | G10: =VLOOKUP(salesdata[[#This Row],[HSN Code]],Table4[#All],2,0) -> Laptop HP xyz i5 | I10: =VLOOKUP(salesdata[[#This Row],[HSN Code]],Table3[#All],6,0) -> 1 | J10: 29 | K10: =VLOOKUP(salesdata[[#This Row],[HSN Code]],Table4[#All],4,0) -> 41400 | L10: =salesdata[[#This Row],[Price]]*salesdata[[#This Row],[Units]] -> 1200600
D11: 102 | E11: =VLOOKUP(salesdata[[#This Row],[Cust_ID]],customersdata[#All],2,0) -> MK Tech. | F11: N1003 | G11: =VLOOKUP(salesdata[[#This Row],[HSN Code]],Table4[#All],2,0) -> Wireless Printer | I11: =VLOOKUP(salesdata[[#This Row],[HSN Code]],Table3[#All],6,0) -> 2 | J11: 38 | K11: =VLOOKUP(salesdata[[#This Row],[HSN Code]],Table4[#All],4,0) -> 5520 | L11: =salesdata[[#This Row],[Price]]*salesdata[[#This Row],[Units]] -> 209760
D12: 103 | E12: =VLOOKUP(salesdata[[#This Row],[Cust_ID]],customersdata[#All],2,0) -> 99store | F12: N1004 | G12: =VLOOKUP(salesdata[[#This Row],[HSN Code]],Table4[#All],2,0) -> Desktop | I12: =VLOOKUP(salesdata[[#This Row],[HSN Code]],Table3[#All],6,0) -> 45 | J12: 55 | K12: =VLOOKUP(salesdata[[#This Row],[HSN Code]],Table4[#All],4,0) -> 25200 | L12: =salesdata[[#This Row],[Price]]*salesdata[[#This Row],[Units]] -> 1386000
D13: 104 | E13: =VLOOKUP(salesdata[[#This Row],[Cust_ID]],customersdata[#All],2,0) -> Rajesh Kumar | F13: N1005 | G13: =VLOOKUP(salesdata[[#This Row],[HSN Code]],Table4[#All],2,0) -> Mouse | I13: =VLOOKUP(salesdata[[#This Row],[HSN Code]],Table3[#All],6,0) -> 1 | J13: 19 | K13: =VLOOKUP(salesdata[[#This Row],[HSN Code]],Table4[#All],4,0) -> 240 | L13: =salesdata[[#This Row],[Price]]*salesdata[[#This Row],[Units]] -> 4560
D14: 105 | E14: =VLOOKUP(salesdata[[#This Row],[Cust_ID]],customersdata[#All],2,0) -> Amit | F14: N1006 | G14: =VLOOKUP(salesdata[[#This Row],[HSN Code]],Table4[#All],2,0) -> Rgb Keyboard | I14: =VLOOKUP(salesdata[[#This Row],[HSN Code]],Table3[#All],6,0) -> 17 | J14: 33 | K14: =VLOOKUP(salesdata[[#This Row],[HSN Code]],Table4[#All],4,0) -> 408 | L14: =salesdata[[#This Row],[Price]]*salesdata[[#This Row],[Units]] -> 13464
D15: 106 | E15: =VLOOKUP(salesdata[[#This Row],[Cust_ID]],customersdata[#All],2,0) -> Jain Tel. | F15: N1007 | G15: =VLOOKUP(salesdata[[#This Row],[HSN Code]],Table4[#All],2,0) -> Camera | I15: =VLOOKUP(salesdata[[#This Row],[HSN Code]],Table3[#All],6,0) -> 3 | J15: 17 | K15: =VLOOKUP(salesdata[[#This Row],[HSN Code]],Table4[#All],4,0) -> 62400 | L15: =salesdata[[#This Row],[Price]]*salesdata[[#This Row],[Units]] -> 1060800

Sheet Inventory
D8: HSN Code | E8: Product Name | F8: Cost | G8: P Units | H8: S Units | I8: Stock | J8: Stock Amount | K8: Notification
D9: =Table4[[#This Row],[HSN Code]] -> N1001 | E9: =Table4[[#This Row],[Product Name]] -> Smart Watch | F9: =Table4[[#This Row],[Cost]] -> 980 | G9: =SUMIF(Purchase!E11:E20,Table3[[#This Row],[Product Name]],Purchase!H11:H20) -> 40 | H9: =SUMIF(salesdata[Product Name],Table3[[#This Row],[Product Name]],salesdata[Units]) -> 27 | I9: =Table3[[#This Row],[P Units]]-Table3[[#This Row],[S Units]] -> 13 | J9: =Table3[[#This Row],[Cost]]*Table3[[#This Row],[Stock]] -> 12740 | K9: =IF(I8<5, "📞 "&E7&" Needs to re-order ! PH "&VLOOKUP(Table3[[#This Row],[HSN Code]],vendorsdata[#All],4,0),"")
D10: =Table4[[#This Row],[HSN Code]] -> N1002 | E10: =Table4[[#This Row],[Product Name]] -> Laptop HP xyz i5 | F10: =Table4[[#This Row],[Cost]] -> 34500 | G10: =SUMIF(Purchase!E12:E21,Table3[[#This Row],[Product Name]],Purchase!H12:H21) -> 30 | H10: =SUMIF(salesdata[Product Name],Table3[[#This Row],[Product Name]],salesdata[Units]) -> 29 | I10: =Table3[[#This Row],[P Units]]-Table3[[#This Row],[S Units]] -> 1 | J10: =Table3[[#This Row],[Cost]]*Table3[[#This Row],[Stock]] -> 34500 | K10: =IF(I9<5, "📞 "&E8&" Needs to re-order ! PH "&VLOOKUP(Table3[[#This Row],[HSN Code]],vendorsdata[#All],4,0),"")
D11: =Table4[[#This Row],[HSN Code]] -> N1003 | E11: =Table4[[#This Row],[Product Name]] -> Wireless Printer | F11: =Table4[[#This Row],[Cost]] -> 4600 | G11: =SUMIF(Purchase!E13:E22,Table3[[#This Row],[Product Name]],Purchase!H13:H22) -> 40 | H11: =SUMIF(salesdata[Product Name],Table3[[#This Row],[Product Name]],salesdata[Units]) -> 38 | I11: =Table3[[#This Row],[P Units]]-Table3[[#This Row],[S Units]] -> 2 | J11: =Table3[[#This Row],[Cost]]*Table3[[#This Row],[Stock]] -> 9200 | K11: =IF(I10<5, "📞 "&E9&" Needs to re-order ! PH "&VLOOKUP(Table3[[#This Row],[HSN Code]],vendorsdata[#All],4,0),"") -> 📞 Smart Watch Needs to re-order ! PH 9812xxxxxx
D12: =Table4[[#This Row],[HSN Code]] -> N1004 | E12: =Table4[[#This Row],[Product Name]] -> Desktop | F12: =Table4[[#This Row],[Cost]] -> 21000 | G12: =SUMIF(Purchase!E14:E23,Table3[[#This Row],[Product Name]],Purchase!H14:H23) -> 100 | H12: =SUMIF(salesdata[Product Name],Table3[[#This Row],[Product Name]],salesdata[Units]) -> 55 | I12: =Table3[[#This Row],[P Units]]-Table3[[#This Row],[S Units]] -> 45 | J12: =Table3[[#This Row],[Cost]]*Table3[[#This Row],[Stock]] -> 945000 | K12: =IF(I11<5, "📞 "&E10&" Needs to re-order ! PH "&VLOOKUP(Table3[[#This Row],[HSN Code]],vendorsdata[#All],4,0),"") -> 📞 Laptop HP xyz i5 Needs to re-order ! PH 9813xxxxxx
D13: =Table4[[#This Row],[HSN Code]] -> N1005 | E13: =Table4[[#This Row],[Product Name]] -> Mouse | F13: =Table4[[#This Row],[Cost]] -> 200 | G13: =SUMIF(Purchase!E15:E24,Table3[[#This Row],[Product Name]],Purchase!H15:H24) -> 20 | H13: =SUMIF(salesdata[Product Name],Table3[[#This Row],[Product Name]],salesdata[Units]) -> 19 | I13: =Table3[[#This Row],[P Units]]-Table3[[#This Row],[S Units]] -> 1 | J13: =Table3[[#This Row],[Cost]]*Table3[[#This Row],[Stock]] -> 200 | K13: =IF(I12<5, "📞 "&E11&" Needs to re-order ! PH "&VLOOKUP(Table3[[#This Row],[HSN Code]],vendorsdata[#All],4,0),"")
D14: =Table4[[#This Row],[HSN Code]] -> N1006 | E14: =Table4[[#This Row],[Product Name]] -> Rgb Keyboard | F14: =Table4[[#This Row],[Cost]] -> 340 | G14: =SUMIF(Purchase!E16:E25,Table3[[#This Row],[Product Name]],Purchase!H16:H25) -> 50 | H14: =SUMIF(salesdata[Product Name],Table3[[#This Row],[Product Name]],salesdata[Units]) -> 33 | I14: =Table3[[#This Row],[P Units]]-Table3[[#This Row],[S Units]] -> 17 | J14: =Table3[[#This Row],[Cost]]*Table3[[#This Row],[Stock]] -> 5780 | K14: =IF(I13<5, "📞 "&E12&" Needs to re-order ! PH "&VLOOKUP(Table3[[#This Row],[HSN Code]],vendorsdata[#All],4,0),"") -> 📞 Desktop Needs to re-order ! PH 9813xxxxxx
D15: =Table4[[#This Row],[HSN Code]] -> N1007 | E15: =Table4[[#This Row],[Product Name]] -> Camera | F15: =Table4[[#This Row],[Cost]] -> 52000 | G15: =SUMIF(Purchase!E17:E26,Table3[[#This Row],[Product Name]],Purchase!H17:H26) -> 20 | H15: =SUMIF(salesdata[Product Name],Table3[[#This Row],[Product Name]],salesdata[Units]) -> 17 | I15: =Table3[[#This Row],[P Units]]-Table3[[#This Row],[S Units]] -> 3 | J15: =Table3[[#This Row],[Cost]]*Table3[[#This Row],[Stock]] -> 156000 | K15: =IF(I14<5, "📞 "&E13&" Needs to re-order ! PH "&VLOOKUP(Table3[[#This Row],[HSN Code]],vendorsdata[#All],4,0),"")
D16: =Table4[[#This Row],[HSN Code]] -> N1008 | E16: =Table4[[#This Row],[Product Name]] -> Headphones | F16: =Table4[[#This Row],[Cost]] -> 799 | G16: =SUMIF(Purchase!E18:E27,Table3[[#This Row],[Product Name]],Purchase!H18:H27) -> 35 | H16: =SUMIF(salesdata[Product Name],Table3[[#This Row],[Product Name]],salesdata[Units]) -> 0 | I16: =Table3[[#This Row],[P Units]]-Table3[[#This Row],[S Units]] -> 35 | J16: =Table3[[#This Row],[Cost]]*Table3[[#This Row],[Stock]] -> 27965 | K16: =IF(I15<5, "📞 "&E14&" Needs to re-order ! PH "&VLOOKUP(Table3[[#This Row],[HSN Code]],vendorsdata[#All],4,0),"") -> 📞 Rgb Keyboard Needs to re-order ! PH 9814xxxxxx
D17: =Table4[[#This Row],[HSN Code]] -> N1009 | E17: =Table4[[#This Row],[Product Name]] -> Speakers | F17: =Table4[[#This Row],[Cost]] -> 670 | G17: =SUMIF(Purchase!E19:E28,Table3[[#This Row],[Product Name]],Purchase!H19:H28) -> 55 | H17: =SUMIF(salesdata[Product Name],Table3[[#This Row],[Product Name]],salesdata[Units]) -> 0 | I17: =Table3[[#This Row],[P Units]]-Table3[[#This Row],[S Units]] -> 55 | J17: =Table3[[#This Row],[Cost]]*Table3[[#This Row],[Stock]] -> 36850 | K17: =IF(I16<5, "📞 "&E15&" Needs to re-order ! PH "&VLOOKUP(Table3[[#This Row],[HSN Code]],vendorsdata[#All],4,0),"")
D18: =Table4[[#This Row],[HSN Code]] -> N1010 | E18: =Table4[[#This Row],[Product Name]] -> Tablets | F18: =Table4[[#This Row],[Cost]] -> 23500 | G18: =SUMIF(Purchase!E20:E29,Table3[[#This Row],[Product Name]],Purchase!H20:H29) -> 40 | H18: =SUMIF(salesdata[Product Name],Table3[[#This Row],[Product Name]],salesdata[Units]) -> 0 | I18: =Table3[[#This Row],[P Units]]-Table3[[#This Row],[S Units]] -> 40 | J18: =Table3[[#This Row],[Cost]]*Table3[[#This Row],[Stock]] -> 940000 | K18: =IF(I17<5, "📞 "&E16&" Needs to re-order ! PH "&VLOOKUP(Table3[[#This Row],[HSN Code]],vendorsdata[#All],4,0),"")

Sheet pivots
A3: Count of Name | C3: Customers | F3: Row Labels | G3: Sum of S Units
A4: 7 | C4: =GETPIVOTDATA("Name",$A$3) -> 7 | F4: Desktop | G4: 55
F5: Wireless Printer | G5: 38
A6: Count of Product Name | C6: Products | F6: Rgb Keyboard | G6: 33
A7: 10 | C7: =GETPIVOTDATA("Product Name",$A$6) -> 10 | F7: Laptop HP xyz i5 | G7: 29
F8: Smart Watch | G8: 27
A9: Sum of Amount | C9: Purchase amount | F9: Grand Total | G9: 182
A10: 5463215 | C10: =GETPIVOTDATA("Amount",$A$9) -> 5463215
A12: Sum of Amount | C12: Sales amount
A13: 3906936 | C13: =GETPIVOTDATA("Amount",$A$12) -> 3906936
F14: Row Labels | G14: Sum of Amount
A15: Sum of Stock Amount | C15: Stock amount | F15: 99store | G15: 1386000
A16: 2168235 | C16: =GETPIVOTDATA("Stock Amount",$A$15) -> 2168235 | F16: Atul Ltd. | G16: 1200600
F17: Jain Tel. | G17: 1060800
C18: profit/loss | F18: MK Tech. | G18: 209760
C19: =C16+C13-C10 -> 611956 | F19: Ram sales | G19: 31752
F20: Grand Total | G20: 3888912
A26: Row Labels | B26: Sum of Stock
A27: Camera | B27: 3
A28: Desktop | B28: 45
A29: Headphones | B29: 35
A30: Laptop HP xyz i5 | B30: 1
A31: Mouse | B31: 1
A32: Rgb Keyboard | B32: 17
A33: Smart Watch | B33: 13
A34: Speakers | B34: 55
A35: Tablets | B35: 40
A36: Wireless Printer | B36: 2
A37: Grand Total | B37: 212
